[
    {
        "Jour": "01-oct",
        "Passager": "156809"
    },
    {
        "Jour": "02-oct",
        "Passager": "164097"
    },
    {
        "Jour": "03-oct",
        "Passager": "136114"
    },
    {
        "Jour": "04-oct",
        "Passager": "141804"
    },
    {
        "Jour": "05-oct",
        "Passager": "146368"
    },
    {
        "Jour": "06-oct",
        "Passager": "172394"
    },
    {
        "Jour": "07-oct",
        "Passager": "109447"
    },
    {
        "Jour": "08-oct",
        "Passager": "141501"
    },
    {
        "Jour": "09-oct",
        "Passager": "168751"
    },
    {
        "Jour": "10-oct",
        "Passager": "147087"
    },
    {
        "Jour": "11-oct",
        "Passager": "148853"
    },
    {
        "Jour": "12-oct",
        "Passager": "187708"
    },
    {
        "Jour": "13-oct",
        "Passager": "184403"
    },
    {
        "Jour": "14-oct",
        "Passager": "109341"
    },
    {
        "Jour": "15-oct",
        "Passager": "127849"
    },
    {
        "Jour": "16-oct",
        "Passager": "165783"
    },
    {
        "Jour": "17-oct",
        "Passager": "146237"
    },
    {
        "Jour": "18-oct",
        "Passager": "143716"
    },
    {
        "Jour": "19-oct",
        "Passager": "170033"
    },
    {
        "Jour": "20-oct",
        "Passager": "214036"
    },
    {
        "Jour": "21-oct",
        "Passager": "124929"
    },
    {
        "Jour": "22-oct",
        "Passager": "150488"
    },
    {
        "Jour": "23-oct",
        "Passager": "145741"
    },
    {
        "Jour": "24-oct",
        "Passager": "150321"
    },
    {
        "Jour": "25-oct",
        "Passager": "140224"
    },
    {
        "Jour": "26-oct",
        "Passager": "185451"
    },
    {
        "Jour": "27-oct",
        "Passager": "208219"
    },
    {
        "Jour": "28-oct",
        "Passager": "144091"
    },
    {
        "Jour": "29-oct",
        "Passager": "183727"
    },
    {
        "Jour": "30-oct",
        "Passager": "178183"
    },
    {
        "Jour": "31-oct",
        "Passager": "148169"
    }
]